Metadata-Version: 1.1
Name: py-email-reply-parser
Version: 0.5.8
Summary: Email reply parser
Home-page: https://github.com/DisruptiveLabs/email-reply-parser
Author: Franklyn Tackitt
Author-email: frank@comanage.com
License: MIT
Platform: UNKNOWN
Classifier: Topic :: Software Development
Classifier: Programming Language :: Python
Classifier: Programming Language :: Python :: 2
Classifier: Programming Language :: Python :: 2.6
Classifier: Programming Language :: Python :: 2.7
Classifier: Programming Language :: Python :: 3
Classifier: Programming Language :: Python :: 3.2
Classifier: Programming Language :: Python :: 3.3
Classifier: Programming Language :: Python :: 3.4
